ShortLanguageDetection/__init__.py
ShortLanguageDetection/main.py
ShortLanguageDetection/DictDetector/__init__.py
ShortLanguageDetection/DictDetector/languages.json
ShortLanguageDetection/DictDetector/main.py
ShortLanguageDetection/DictDetector/dict/ar.txt
ShortLanguageDetection/DictDetector/dict/bg.txt
ShortLanguageDetection/DictDetector/dict/ca.txt
ShortLanguageDetection/DictDetector/dict/cz.txt
ShortLanguageDetection/DictDetector/dict/da.txt
ShortLanguageDetection/DictDetector/dict/de.txt
ShortLanguageDetection/DictDetector/dict/el.txt
ShortLanguageDetection/DictDetector/dict/en.txt
ShortLanguageDetection/DictDetector/dict/es.txt
ShortLanguageDetection/DictDetector/dict/fi.txt
ShortLanguageDetection/DictDetector/dict/fr.txt
ShortLanguageDetection/DictDetector/dict/hi.txt
ShortLanguageDetection/DictDetector/dict/hu.txt
ShortLanguageDetection/DictDetector/dict/id.txt
ShortLanguageDetection/DictDetector/dict/it.txt
ShortLanguageDetection/DictDetector/dict/nb.txt
ShortLanguageDetection/DictDetector/dict/nl.txt
ShortLanguageDetection/DictDetector/dict/pl.txt
ShortLanguageDetection/DictDetector/dict/pt.txt
ShortLanguageDetection/DictDetector/dict/ro.txt
ShortLanguageDetection/DictDetector/dict/ru.txt
ShortLanguageDetection/DictDetector/dict/sk.txt
ShortLanguageDetection/DictDetector/dict/sv.txt
ShortLanguageDetection/DictDetector/dict/tr.txt
ShortLanguageDetection/DictDetector/dict/uk.txt
ShortLanguageDetection/DictDetector/dict/vi.txt
ShortLanguageDetection/models/discord_langdetect.ftz
ShortLanguageDetection/models/langdetect.ftz
ShortLanguageDetection/models/lid.176.ftz
ShortLanguageDetection-0.0.9.dist-info/LICENSE
ShortLanguageDetection-0.0.9.dist-info/METADATA
ShortLanguageDetection-0.0.9.dist-info/WHEEL
ShortLanguageDetection-0.0.9.dist-info/top_level.txt
ShortLanguageDetection-0.0.9.dist-info/RECORD
