Metadata-Version: 2.1
Name: ShortLanguageDetection
Version: 0.0.9
Summary: A language detector for short string or chat.
Home-page: https://github.com/Interaction-Bot/LanguageDetection/
Author: Jourdelune
License: MIT
Keywords: language,detection,nlp,identification,short
License-File: LICENSE
Requires-Dist: fasttext-wheel
Requires-Dist: emoji
Requires-Dist: lingua-language-detector
